AM_PM_to_HM_converter/AM_PM_to_24.py
AM_PM_to_HM_converter-0.0.1.dist-info/LICENSE
AM_PM_to_HM_converter-0.0.1.dist-info/METADATA
AM_PM_to_HM_converter-0.0.1.dist-info/WHEEL
AM_PM_to_HM_converter-0.0.1.dist-info/entry_points.txt
AM_PM_to_HM_converter-0.0.1.dist-info/top_level.txt
AM_PM_to_HM_converter-0.0.1.dist-info/RECORD
