Metadata-Version: 2.1
Name: AM-PM-to-HM-converter
Version: 0.0.1
Summary: A Python package to convert AM PM time mode to 24 hours mode.
Home-page: https://github.com/aniket-coder-arch/AM-PM-to-HM-converter
Author: Aniket Dubey
Author-email: daniket182@gmail.com
License: MIT
Platform: UNKNOWN
Classifier: License :: OSI Approved :: MIT License
Classifier: Programming Language :: Python :: 3
Classifier: Programming Language :: Python :: 3.7
Requires-Dist: nltk
